yaoauth2/__init__.py
yaoauth2/config.py
yaoauth2/endpoints.py
yaoauth2/models.py
yaoauth2/providers/__init__.py
yaoauth2/providers/discord.py
yaoauth2/providers/google.py
yaoauth2/router.py
yaoauth2/utils.py
yaoauth2-1.1.2.dist-info/WHEEL
yaoauth2-1.1.2.dist-info/METADATA
yaoauth2-1.1.2.dist-info/RECORD
